LICENSE
MANIFEST.in
README.md
setup.py
django_cradmin/__init__.py
django_cradmin/context_processors.py
django_cradmin/cradmin_testhelpers.py
django_cradmin/crapp.py
django_cradmin/crbreadcrumb.py
django_cradmin/crfooter.py
django_cradmin/crheader.py
django_cradmin/crinstance.py
django_cradmin/crmenu.py
django_cradmin/crsettings.py
django_cradmin/css_icon_map.py
django_cradmin/datetimeutils.py
django_cradmin/decorators.py
django_cradmin/delay_middleware.py
django_cradmin/messages_debug_middleware.py
django_cradmin/models.py
django_cradmin/registry.py
django_cradmin/renderable.py
django_cradmin/urlutils.py
django_cradmin/version.json
django_cradmin.egg-info/PKG-INFO
django_cradmin.egg-info/SOURCES.txt
django_cradmin.egg-info/dependency_links.txt
django_cradmin.egg-info/not-zip-safe
django_cradmin.egg-info/requires.txt
django_cradmin.egg-info/top_level.txt
django_cradmin/acemarkdown/__init__.py
django_cradmin/acemarkdown/widgets.py
django_cradmin/apps/__init__.py
django_cradmin/apps/cradmin_activate_account/__init__.py
django_cradmin/apps/cradmin_activate_account/urls.py
django_cradmin/apps/cradmin_activate_account/utils.py
django_cradmin/apps/cradmin_activate_account/templates/cradmin_activate_account/activate.django.html
django_cradmin/apps/cradmin_activate_account/templates/cradmin_activate_account/email/html_message.django.html
django_cradmin/apps/cradmin_activate_account/templates/cradmin_activate_account/email/subject.django.txt
django_cradmin/apps/cradmin_activate_account/templates/cradmin_activate_account/messages/activation-link-expired.django.html
django_cradmin/apps/cradmin_activate_account/templates/cradmin_activate_account/messages/activation-link-invalid.django.html
django_cradmin/apps/cradmin_activate_account/templates/cradmin_activate_account/messages/success.django.html
django_cradmin/apps/cradmin_activate_account/tests/__init__.py
django_cradmin/apps/cradmin_activate_account/tests/test_activate.py
django_cradmin/apps/cradmin_activate_account/tests/test_utils.py
django_cradmin/apps/cradmin_activate_account/views/__init__.py
django_cradmin/apps/cradmin_activate_account/views/activate.py
django_cradmin/apps/cradmin_authenticate/__init__.py
