Metadata-Version: 2.1
Name: django-cradmin
Version: 10.0.1
Summary: A role based admin UI for Django that produces a user friendly and beautiful UI.
Home-page: https://github.com/appressoas/django_cradmin
Author: Espen Angell Kristiansen, Tor Johansen, Vegard Angell, Magne Westlie
Author-email: post@appresso.no
License: BSD
Classifier: Development Status :: 4 - Beta
Classifier: Environment :: Web Environment
Classifier: Framework :: Django
Classifier: Intended Audience :: Developers
Classifier: License :: OSI Approved
Classifier: Operating System :: OS Independent
Classifier: Programming Language :: Python
License-File: LICENSE
